{"kind": "youtube#videoListResponse", "etag": "\"tnVOtk4NeGU6nDncDTE5m9SmuHc/S4tFx6_eHKYvzNInBtvzB3HonZI\"", "pageInfo": {"totalResults": 1, "resultsPerPage": 1}, "items": [{"kind": "youtube#video", "etag": "\"tnVOtk4NeGU6nDncDTE5m9SmuHc/jcAwHbz1Ydh4zGVDVT_iO3JUxdU\"", "id": "gGf7kFBzC48", "snippet": {"publishedAt": "2015-09-30T19:39:51.000Z", "channelId": "UCtBtcQJ8_jsrjPzb8i1tOsA", "title": "How to Graph a Quadratic and Find Intercepts, Vertex, & Axis of Symmetry!", "description": "On this lesson, you fill learn how to graph a quadratic function, find the axis of symmetry, vertex, and the x intercepts and y intercepts of a parabola...without a graphing calculator!\n\nThis lesson answers the following questions: What is a quadratic function? What does a quadratic function look like? What is a quadratic equation? How do I find the vertex of a parabola? How do I find axis of symmetry? How do I find x and y intercepts of a function?\n\nBe sure to join our mailing list at http://www.mashupmath.com", "thumbnails": {"default": {"url": "https://i.ytimg.com/vi/gGf7kFBzC48/default.jpg", "width": 120, "height": 90}, "medium": {"url": "https://i.ytimg.com/vi/gGf7kFBzC48/mqdefault.jpg", "width": 320, "height": 180}, "high": {"url": "https://i.ytimg.com/vi/gGf7kFBzC48/hqdefault.jpg", "width": 480, "height": 360}, "standard": {"url": "https://i.ytimg.com/vi/gGf7kFBzC48/sddefault.jpg", "width": 640, "height": 480}, "maxres": {"url": "https://i.ytimg.com/vi/gGf7kFBzC48/maxresdefault.jpg", "width": 1280, "height": 720}}, "channelTitle": "MashUp Math", "tags": ["graph a quadratic", "graph a quadratic function", "graph a quadratic function in vertex form", "graph a quadratic function in standard form", "graph a quadratic function using its vertex axis and intercepts", "graph a quadratic equation in vertex form", "graph a quadratic in standard form", "graph a parabola", "axis of symmetry", "axis of symmetry formula", "how to find", "x intercepts of a parabola", "x intercepts", "y intercepts of a parabola", "y intercepts", "vertex", "parabola", "vertex of quadratic function"], "categoryId": "27", "liveBroadcastContent": "none", "localized": {"title": "How to Graph a Quadratic and Find Intercepts, Vertex, & Axis of Symmetry!", "description": "On this lesson, you fill learn how to graph a quadratic function, find the axis of symmetry, vertex, and the x intercepts and y intercepts of a parabola...without a graphing calculator!\n\nThis lesson answers the following questions: What is a quadratic function? What does a quadratic function look like? What is a quadratic equation? How do I find the vertex of a parabola? How do I find axis of symmetry? How do I find x and y intercepts of a function?\n\nBe sure to join our mailing list at http://www.mashupmath.com"}, "defaultAudioLanguage": "en"}}]}
