{"kind": "youtube#videoListResponse", "etag": "\"tnVOtk4NeGU6nDncDTE5m9SmuHc/7jWq9UnfNS4DtzxfdUnBD3GagzE\"", "pageInfo": {"totalResults": 1, "resultsPerPage": 1}, "items": [{"kind": "youtube#video", "etag": "\"tnVOtk4NeGU6nDncDTE5m9SmuHc/aJ4at5t6w7TaRNWuc_ZsFtevhGw\"", "id": "h7ZAQfNh8XA", "snippet": {"publishedAt": "2016-09-07T15:00:04.000Z", "channelId": "UCtBtcQJ8_jsrjPzb8i1tOsA", "title": "DIFFERENCE BETWEEN SIMILAR & CONGRUENT FIGURES?", "description": "Let's explore the difference between similar and congruent figures (similarity vs. congruence) in this conceptual mini-lesson.\n\n★ Want more FREE weekly math videos? Subscribe Now: http://bit.ly/1OVJnyh\n\n★★ Why Math? Download YOUR Free eBook and sign-up for our FREE weekly newsletter: http://www.mashupmath.com/resources/\n\n★★★ Learn More About Anthony: http://bit.ly/1KQ1Td3\n\nUnderstand congruence and similarity using physical models, transparencies, or geometry software.\n\nUnderstand that a two-dimensional figure is similar to another if the second can be obtained from the first by a sequence of rotations, reflections, translations, and dilations; given two similar two-dimensional figures, describe a sequence that exhibits the similarity between them.\n\nWhat does it mean when two figures are similar?\nWhat does it mean when two figures are congruent?\nWhat is the difference between similarity and conrguence?\n\nImage Credit: Emojis provided free by http://emojione.com\n\n✔✔✔SUBSCRIBE FOR FREE: https://www.youtube.com/channel/UCtBt...\n\n✔✔JOIN OUR MAILING LIST: http://bit.ly/1TqV94V\n\n✔FOLLOW US ON TWITTER: http://www.twitter.com/mashupmath\n✔FOLLOW US ON INSTAGRAM: http://www.instagram.com/mashupmath\n✔FOLLOW US ON PINTEREST: http://www.pinterest.com/mashupmath\n✔LIKE US ON FACEBOOK: http://www.facebook.com/mashupmath", "thumbnails": {"default": {"url": "https://i.ytimg.com/vi/h7ZAQfNh8XA/default.jpg", "width": 120, "height": 90}, "medium": {"url": "https://i.ytimg.com/vi/h7ZAQfNh8XA/mqdefault.jpg", "width": 320, "height": 180}, "high": {"url": "https://i.ytimg.com/vi/h7ZAQfNh8XA/hqdefault.jpg", "width": 480, "height": 360}, "standard": {"url": "https://i.ytimg.com/vi/h7ZAQfNh8XA/sddefault.jpg", "width": 640, "height": 480}, "maxres": {"url": "https://i.ytimg.com/vi/h7ZAQfNh8XA/maxresdefault.jpg", "width": 1280, "height": 720}}, "channelTitle": "MashUp Math", "tags": ["yt:quality=high", "similar figures", "congruent figures", "similar vs congruent", "similar vs congruent triangles", "similar vs congruent shapes", "similar vs congruent figures", "similar polygons", "similar definition math", "similarity definition", "congruent definition geometry", "congruent definition math", "figures that are congruent or similar", "common core math", "math antics", "khan academy", "congruent figures math antics", "congruent figures song", "congruent figures and similar figures", "homeschool"], "categoryId": "27", "liveBroadcastContent": "none", "localized": {"title": "DIFFERENCE BETWEEN SIMILAR & CONGRUENT FIGURES?", "description": "Let's explore the difference between similar and congruent figures (similarity vs. congruence) in this conceptual mini-lesson.\n\n★ Want more FREE weekly math videos? Subscribe Now: http://bit.ly/1OVJnyh\n\n★★ Why Math? Download YOUR Free eBook and sign-up for our FREE weekly newsletter: http://www.mashupmath.com/resources/\n\n★★★ Learn More About Anthony: http://bit.ly/1KQ1Td3\n\nUnderstand congruence and similarity using physical models, transparencies, or geometry software.\n\nUnderstand that a two-dimensional figure is similar to another if the second can be obtained from the first by a sequence of rotations, reflections, translations, and dilations; given two similar two-dimensional figures, describe a sequence that exhibits the similarity between them.\n\nWhat does it mean when two figures are similar?\nWhat does it mean when two figures are congruent?\nWhat is the difference between similarity and conrguence?\n\nImage Credit: Emojis provided free by http://emojione.com\n\n✔✔✔SUBSCRIBE FOR FREE: https://www.youtube.com/channel/UCtBt...\n\n✔✔JOIN OUR MAILING LIST: http://bit.ly/1TqV94V\n\n✔FOLLOW US ON TWITTER: http://www.twitter.com/mashupmath\n✔FOLLOW US ON INSTAGRAM: http://www.instagram.com/mashupmath\n✔FOLLOW US ON PINTEREST: http://www.pinterest.com/mashupmath\n✔LIKE US ON FACEBOOK: http://www.facebook.com/mashupmath"}, "defaultAudioLanguage": "en"}}]}
